rrai/__init__.py
rrai/case_studies.py
rrai-1.0.0.dist-info/licenses/LICENSE
rrai-1.0.0.dist-info/METADATA
rrai-1.0.0.dist-info/WHEEL
rrai-1.0.0.dist-info/top_level.txt
rrai-1.0.0.dist-info/RECORD
